{
  "Dog Squad A": {
    "positions": {
      "1": "Morvessa",
      "2": "Tex",
      "3": "Darkspy",
      "4": "Magicguy",
      "5": "Samson",
      "6": "BlindGuy",
      "7": "brewdog",
      "8": "Abdullah"
    },
    "mm": [
      "Tex",
      "Sparta",
      "",
      "",
      "",
      ""
    ],
    "ce": [
      "",
      ""
    ],
    "goon": [
      "Sparta",
      "Peewee",
      "J",
      "Mephisto",
      "WOOOOOO",
      "Dtp20"
    ],
    "standby": [
      "Madmaxx",
      "Biggie",
      "MF_Bluey",
      "Smurfx"
    ],
    "hover": [
      "Jopn17tl",
      "HourPa"
    ],
    "crystal": [
      "Gorilla",
      "Mopar"
    ],
    "notes": "fk boats"
  },
  "Dog Squad B": {
    "positions": {
      "1": "Thor",
      "2": "Mulan",
      "3": "Wonka",
      "4": "Drak",
      "5": "cardsfan",
      "6": "Nembo",
      "7": "Talion",
      "8": "Pete"
    },
    "goon": [
      "CHAUSUI",
      "Otts",
      "Lady",
      "AlexMat",
      "Demon",
      "Jerky"
    ],
    "standby": [
      "MONKEY",
      "Maximum (DOG)",
      "Aresu",
      "HELLFIRE",
      "Shorty"
    ],
    "hover": [
      "Bchara",
      "Motyer"
    ],
    "crystal": [
      "DragonMC",
      "joske"
    ],
    "notes": ""
  }
}